{
    "success": true,
    "station": "movies",
    "items": [{
            "id": 6,
            "name": "Star Wars Ep. IV",
            "excerpt": "Star Wars from George Lucas",
            "price": 150,
            "url": "https://snuuper.s3.amazonaws.com/snuuperTest/android-tv-6.jpg"
        }, {
            "id": 7,
            "name": "Seven Samurai",
            "excerpt": "Seven Samurai from Akira Kurosawa",
            "price": 150,
            "url": "https://snuuper.s3.amazonaws.com/snuuperTest/7samurai2.jpg"
        },
        {
            "id": 8,
            "name": "A Clockwork Orange",
            "excerpt": "A Clockwork Orange from Stanley Kubrick",
            "price": 150,
            "url": "https://snuuper.s3.amazonaws.com/snuuperTest/clockwork.jpg"
        }, {
            "id": 9,
            "name": "300",
            "excerpt": "300 from Zack Snyder",
            "price": 150,
            "url": "https://snuuper.s3.amazonaws.com/snuuperTest/300.jpg"
        },
        {
            "id": 10,
            "name": "The Terminator",
            "excerpt": "The Terminator from James Cameron",
            "price": 150,
            "url": "https://snuuper.s3.amazonaws.com/snuuperTest/the-terminator-1.jpg"
        }
    ]
}